{"date": "2015/Dec/1 Tue 22:09:59", "msg": "Sync app started"},
{"date": "2015/Dec/1 Tue 22:10:02", "msg": "Starting sync of SpaceExp"},
{"date": "2015/Dec/1 Tue 22:10:03", "msg": "Sync of SpaceExp finished"},
{"date": "2015/Dec/23 Wed 23:43:12", "msg": "Sync app started"},
{"date": "2015/Dec/23 Wed 23:43:32", "msg": "Starting sync of SpaceExp"},
{"date": "2015/Dec/23 Wed 23:43:34", "msg": "Sync of SpaceExp finished"},
{"date": "2015/Dec/23 Wed 23:48:52", "msg": "Sync app started"},
{"date": "2015/Dec/23 Wed 23:48:56", "msg": "Starting sync of SpaceExp"},
{"date": "2015/Dec/23 Wed 23:49:27", "msg": "Sync of SpaceExp finished"}