
{
	"data":{
		"name":"PipeRings2",
		"target":"RPrg",
		"path":"programs.path",
		
		"data":{
			"PipeRings2":{
				"params":{"pathFunc":"Random","pathCurveLength":200,"cycleLength":7200,
					"texADelay":4
				},
				"streams":[
				{
						"cn":"StreamObjs",
						"name":"Multi Balls",
						"gap":240,
						"active":true,
						"prgObj":{
							"cn":"SimpleObj",
							"geom":"FlatRing240",
							"mat":["Cloud","C3D",{"q":"A"},{}],
							//"rot":1,
							"rotZ":["Stepper",[0.3,-0.3]],
							"trans":{
								"scale":["Stepper",[1,1],{"delay":1}]
								//"_prg":[["x","y","rotationZ"],"Circle2D",{"radius":100,"alphaStep":120}]
								},

						}
					},
					{
						"cn":"StreamObjs",
						"name":"Multi Balls",
						"gap":120,
						"active":true,
						"prgObj":{
							"cn":"SimpleObj",
							"geom":"geomTorus4Slim",
							"mat":"MCBW100",
							//"rot":1,
							
							"trans":{
								"scale":0.7
								//"_prg":[["x","y","rotationZ"],"Circle2D",{"radius":100,"alphaStep":120}]
								},
							"gap":240
						}
					}
				]
			}
		}
	}
}